{
  "name": "doc-coauthoring",
  "description": "Guide users through a structured workflow for co-authoring documentation. Use when user wants to write documentation, proposals, technical specs, decision docs, or similar structured content. This workflow helps users efficiently transfer context, refine content through iteration, and verify the doc works for readers. Trigger when user mentions writing docs, creating proposals, drafting specs, or similar documentation tasks.",
  "head": "3d59511518591fa82e6cfcf0438d68dd5dad3e76",
  "updatedAt": "2026-02-28T03:59:24Z",
  "checkedAt": "2026-02-28T03:59:24Z"
}
